Workbook

Sheet Tasks
A1: # | B1: Task | C1: Sheet | D1: Hint (functions) | E1: Your Answer
A2: 1 | B2: Calculate Net Sales for every row (Qty x Unit Price x (1 - Discount)). | C2: Sales Data (col G) | D2: Basic formula, fill down | E2: Done
A3: 2 | B3: Fetch the City for every row using Store ID. | C3: Sales Data (col H) | D3: VLOOKUP or INDEX/MATCH | E3: Done
A4: 3 | B4: Flag rows with discount above 20% as 'Yes', else 'No'. | C4: Sales Data (col I) | D4: IF | E4: Done
A5: 4 | B5: Calculate Purchase Value for every purchase row. | C5: Purchase Data (col G) | D5: Qty x Cost Price | E5: Done
A6: 5 | B6: What is the total net sales? | C6: Sales Data | D6: SUM | E6: =SUM('Sales Data'!G2:G201) -> 2846770
A7: 6 | B7: What is the average net sales per transaction? | C7: Sales Data | D7: AVERAGE | E7: =E6/COUNTA('Sales Data'!G2:G201) -> 14233.85
A8: 7 | B8: Net sales for each store (S01 to S06). Which store is the top performer? | C8: Sales Data | D8: SUMIFS, MAX, INDEX/MATCH | E8: Bengaluru
A9: 8 | B9: Month-wise net sales for Aug, Sep and Oct 2026. | C9: Sales Data | D9: Pivot table (group by month) or SUMIFS with dates | E9: Done
A10: 9 | B10: How many transactions had a discount above 20%? | C10: Sales Data | D10: COUNTIF | E10: =COUNTIF('Sales Data'!F2:F201,">20%") -> 40
A11: 10 | B11: Total value of purchases not yet received. | C11: Purchase Data | D11: SUMIFS | E11: =SUMIF('Purchase Data'!F2:F61,"No",'Purchase Data'!G2:G61) -> 2033750
A12: 11 | B12: Category-wise stock balance = received purchase qty - sold qty. | C12: Both sheets | D12: SUMIFS | E12: Done
A13: 12 | B13: Build a pivot table: Store (rows) x Category (columns), values = Net Sales. | C13: Sales Data | D13: Insert > PivotTable | E13: Done
A14: 13 | B14: Highlight stores with net sales below the average of all stores. | C14: Your store summary | D14: Conditional Formatting | E14: Done
A15: 14 | B15: Clean the Messy Data sheet: remove extra spaces, proper case names and cities, remove duplicates. | C15: Messy Data | D15: TRIM, PROPER, Remove Duplicates | E15: Done

Sheet Store Master
A1: Store ID | B1: City | C1: State | D1: Manager | E1: net sales | G1: average netsales | I1: Month | J1: month | K1: Net Sales
A2: S01 | B2: Hyderabad | C2: Telangana | D2: Ravi Kumar | E2: =SUMIF('Sales Data'!$B$2:$B$201,'Store Master'!A2,'Sales Data'!$G$2:$G$201) -> 550335 | G2: =AVERAGE(E2:E7) -> 474461.67 | I2: August | J2: 8 | K2: =SUMIF('Sales Data'!J2:J201,'Store Master'!J2,'Sales Data'!G2:G201) -> 1479847.5
A3: S02 | B3: Vijayawada | C3: Andhra Pradesh | D3: Sneha Reddy | E3: =SUMIF('Sales Data'!$B$2:$B$201,'Store Master'!A3,'Sales Data'!$G$2:$G$201) -> 312112.5 | I3: September | J3: 9 | K3: =SUMIF('Sales Data'!J3:J202,'Store Master'!J3,'Sales Data'!G3:G202) -> 861295
A4: S03 | B4: Visakhapatnam | C4: Andhra Pradesh | D4: Anil Varma | E4: =SUMIF('Sales Data'!$B$2:$B$201,'Store Master'!A4,'Sales Data'!$G$2:$G$201) -> 396017.5 | I4: October | J4: 10 | K4: =SUMIF('Sales Data'!J4:J203,'Store Master'!J4,'Sales Data'!G4:G203) -> 505627.5
A5: S04 | B5: Bengaluru | C5: Karnataka | D5: Meena Iyer | E5: =SUMIF('Sales Data'!$B$2:$B$201,'Store Master'!A5,'Sales Data'!$G$2:$G$201) -> 715822.5
A6: S05 | B6: Chennai | C6: Tamil Nadu | D6: Karthik Raj | E6: =SUMIF('Sales Data'!$B$2:$B$201,'Store Master'!A6,'Sales Data'!$G$2:$G$201) -> 510697.5
A7: S06 | B7: Warangal | C7: Telangana | D7: Lakshmi Devi | E7: =SUMIF('Sales Data'!$B$2:$B$201,'Store Master'!A7,'Sales Data'!$G$2:$G$201) -> 361785
E8: =SUM(E2:E7) -> 2846770
E9: =MAX(E2:E7) -> 715822.5 | I9: Category | J9: Received purchase | K9: sold quantity | L9: Stock quantity
I10: Dress Material | J10: =SUMIFS('Purchase Data'!$D$2:$D$61,'Purchase Data'!$F$2:$F$61,"Yes",'Purchase Data'!$C$2:$C$61,'Store Master'!I10) -> 159 | K10: =SUMIF('Sales Data'!$C$2:$C$201,'Store Master'!I10,'Sales Data'!$D$2:$D$201) -> 84 | L10: =J10-K10 -> 75
I11: Kids Wear | J11: =SUMIFS('Purchase Data'!$D$2:$D$61,'Purchase Data'!$F$2:$F$61,"Yes",'Purchase Data'!$C$2:$C$61,'Store Master'!I11) -> 274 | K11: =SUMIF('Sales Data'!$C$2:$C$201,'Store Master'!I11,'Sales Data'!$D$2:$D$201) -> 96 | L11: =J11-K11 -> 178
I12: Lehenga | J12: =SUMIFS('Purchase Data'!$D$2:$D$61,'Purchase Data'!$F$2:$F$61,"Yes",'Purchase Data'!$C$2:$C$61,'Store Master'!I12) -> 317 | K12: =SUMIF('Sales Data'!$C$2:$C$201,'Store Master'!I12,'Sales Data'!$D$2:$D$201) -> 90 | L12: =J12-K12 -> 227
I13: Menswear | J13: =SUMIFS('Purchase Data'!$D$2:$D$61,'Purchase Data'!$F$2:$F$61,"Yes",'Purchase Data'!$C$2:$C$61,'Store Master'!I13) -> 194 | K13: =SUMIF('Sales Data'!$C$2:$C$201,'Store Master'!I13,'Sales Data'!$D$2:$D$201) -> 81 | L13: =J13-K13 -> 113
I14: Silk Saree | J14: =SUMIFS('Purchase Data'!$D$2:$D$61,'Purchase Data'!$F$2:$F$61,"Yes",'Purchase Data'!$C$2:$C$61,'Store Master'!I14) -> 482 | K14: =SUMIF('Sales Data'!$C$2:$C$201,'Store Master'!I14,'Sales Data'!$D$2:$D$201) -> 59 | L14: =J14-K14 -> 423

Sheet Pivot Table
A3: Sum of Net Sales | B3: Category
A4: Stores | B4: Dress Material | C4: Kids Wear | D4: Lehenga | E4: Menswear | F4: Silk Saree | G4: Grand Total
A5: S01 | B5: 39770 | C5: 12435 | D5: 365525 | E5: 28205 | F5: 104400 | G5: 550335
A6: S02 | B6: 17160 | C6: 24670 | D6: 136905 | E6: 33745 | F6: 99632.5 | G6: 312112.5
A7: S03 | B7: 18982.5 | C7: 27967.5 | D7: 270330 | E7: 38432.5 | F7: 40305 | G7: 396017.5
A8: S04 | B8: 55570 | C8: 42567.5 | D8: 431337.5 | E8: 60980 | F8: 125367.5 | G8: 715822.5
A9: S05 | B9: 26587.5 | C9: 30742.5 | D9: 294335 | E9: 45722.5 | F9: 113310 | G9: 510697.5
A10: S06 | B10: 22520 | C10: 58060 | D10: 188937.5 | E10: 59007.5 | F10: 33260 | G10: 361785
A11: Grand Total | B11: 180590 | C11: 196442.5 | D11: 1687370 | E11: 266092.5 | F11: 516275 | G11: 2846770

Sheet Sales Data
A1: Date | B1: Store ID | C1: Category | D1: Qty | E1: Unit Price | F1: Discount % | G1: Net Sales | H1: City | I1: High Discount? | J1: month
A2: 46235 | B2: S06 | C2: Kids Wear | D2: 1 | E2: 2850 | F2: 0.3 | G2: =D2*E2*(1-F2) -> 1995 | H2: =VLOOKUP(B2,'Store Master'!$A$2:$B$7,2,0) -> Warangal | I2: =IF(F2>20%,"Yes","No") -> Yes | J2: =MONTH(A2) -> 8
A3: 46235 | B3: S04 | C3: Menswear | D3: 2 | E3: 5350 | F3: 0 | G3: =D3*E3*(1-F3) -> 10700 | H3: =VLOOKUP(B3,'Store Master'!$A$2:$B$7,2,0) -> Bengaluru | I3: =IF(F3>20%,"Yes","No") -> No | J3: =MONTH(A3) -> 8
A4: 46235 | B4: S06 | C4: Dress Material | D4: 2 | E4: 2800 | F4: 0 | G4: =D4*E4*(1-F4) -> 5600 | H4: =VLOOKUP(B4,'Store Master'!$A$2:$B$7,2,0) -> Warangal | I4: =IF(F4>20%,"Yes","No") -> No | J4: =MONTH(A4) -> 8
A5: 46235 | B5: S03 | C5: Kids Wear | D5: 3 | E5: 3200 | F5: 0.25 | G5: =D5*E5*(1-F5) -> 7200 | H5: =VLOOKUP(B5,'Store Master'!$A$2:$B$7,2,0) -> Visakhapatnam | I5: =IF(F5>20%,"Yes","No") -> Yes | J5: =MONTH(A5) -> 8
A6: 46236 | B6: S04 | C6: Dress Material | D6: 1 | E6: 3200 | F6: 0 | G6: =D6*E6*(1-F6) -> 3200 | H6: =VLOOKUP(B6,'Store Master'!$A$2:$B$7,2,0) -> Bengaluru | I6: =IF(F6>20%,"Yes","No") -> No | J6: =MONTH(A6) -> 8
A7: 46236 | B7: S06 | C7: Dress Material | D7: 3 | E7: 2150 | F7: 0 | G7: =D7*E7*(1-F7) -> 6450 | H7: =VLOOKUP(B7,'Store Master'!$A$2:$B$7,2,0) -> Warangal | I7: =IF(F7>20%,"Yes","No") -> No | J7: =MONTH(A7) -> 8
A8: 46238 | B8: S05 | C8: Lehenga | D8: 3 | E8: 32450 | F8: 0.3 | G8: =D8*E8*(1-F8) -> 68145 | H8: =VLOOKUP(B8,'Store Master'!$A$2:$B$7,2,0) -> Chennai | I8: =IF(F8>20%,"Yes","No") -> Yes | J8: =MONTH(A8) -> 8
A9: 46238 | B9: S01 | C9: Lehenga | D9: 3 | E9: 24550 | F9: 0 | G9: =D9*E9*(1-F9) -> 73650 | H9: =VLOOKUP(B9,'Store Master'!$A$2:$B$7,2,0) -> Hyderabad | I9: =IF(F9>20%,"Yes","No") -> No | J9: =MONTH(A9) -> 8
A10: 46238 | B10: S04 | C10: Kids Wear | D10: 3 | E10: 2450 | F10: 0.05 | G10: =D10*E10*(1-F10) -> 6982.5 | H10: =VLOOKUP(B10,'Store Master'!$A$2:$B$7,2,0) -> Bengaluru | I10: =IF(F10>20%,"Yes","No") -> No | J10: =MONTH(A10) -> 8
A11: 46238 | B11: S04 | C11: Kids Wear | D11: 2 | E11: 1550 | F11: 0.1 | G11: =D11*E11*(1-F11) -> 2790 | H11: =VLOOKUP(B11,'Store Master'!$A$2:$B$7,2,0) -> Bengaluru | I11: =IF(F11>20%,"Yes","No") -> No | J11: =MONTH(A11) -> 8
A12: 46238 | B12: S01 | C12: Kids Wear | D12: 2 | E12: 1050 | F12: 0.15 | G12: =D12*E12*(1-F12) -> 1785 | H12: =VLOOKUP(B12,'Store Master'!$A$2:$B$7,2,0) -> Hyderabad | I12: =IF(F12>20%,"Yes","No") -> No | J12: =MONTH(A12) -> 8
A13: 46239 | B13: S01 | C13: Silk Saree | D13: 1 | E13: 8100 | F13: 0.3 | G13: =D13*E13*(1-F13) -> 5670 | H13: =VLOOKUP(B13,'Store Master'!$A$2:$B$7,2,0) -> Hyderabad | I13: =IF(F13>20%,"Yes","No") -> Yes | J13: =MONTH(A13) -> 8
... A201: 46308 | B201: S01 | C201: Lehenga | D201: 3 | E201: 24400 | F201: 0.25 | G201: =D201*E201*(1-F201) -> 54900 | H201: =VLOOKUP(B201,'Store Master'!$A$2:$B$7,2,0) -> Hyderabad | I201: =IF(F201>20%,"Yes","No") -> Yes | J201: =MONTH(A201) -> 10

Sheet Purchase Data
A1: Date | B1: Supplier | C1: Category | D1: Qty | E1: Cost Price | F1: Received? | G1: Purchase Value
A2: 46235 | B2: Surat Textiles | C2: Lehenga | D2: 59 | E2: 9900 | F2: Yes | G2: =D2*E2 -> 584100
A3: 46238 | B3: Banaras Looms | C3: Lehenga | D3: 60 | E3: 5200 | F3: Yes | G3: =D3*E3 -> 312000
A4: 46239 | B4: Pochampally Co-op | C4: Kids Wear | D4: 38 | E4: 900 | F4: Yes | G4: =D4*E4 -> 34200
A5: 46240 | B5: Pochampally Co-op | C5: Silk Saree | D5: 17 | E5: 7450 | F5: Yes | G5: =D5*E5 -> 126650
A6: 46241 | B6: Surat Textiles | C6: Kids Wear | D6: 60 | E6: 950 | F6: Yes | G6: =D6*E6 -> 57000
A7: 46241 | B7: Mysore Silks | C7: Lehenga | D7: 13 | E7: 7550 | F7: Yes | G7: =D7*E7 -> 98150
A8: 46242 | B8: Surat Textiles | C8: Menswear | D8: 17 | E8: 1950 | F8: No | G8: =D8*E8 -> 33150
A9: 46243 | B9: Mysore Silks | C9: Dress Material | D9: 23 | E9: 900 | F9: Yes | G9: =D9*E9 -> 20700
A10: 46243 | B10: Ludhiana Garments | C10: Lehenga | D10: 11 | E10: 17100 | F10: Yes | G10: =D10*E10 -> 188100
A11: 46244 | B11: Surat Textiles | C11: Lehenga | D11: 53 | E11: 17300 | F11: No | G11: =D11*E11 -> 916900
A12: 46246 | B12: Ludhiana Garments | C12: Lehenga | D12: 48 | E12: 15450 | F12: Yes | G12: =D12*E12 -> 741600
A13: 46247 | B13: Pochampally Co-op | C13: Silk Saree | D13: 38 | E13: 6000 | F13: Yes | G13: =D13*E13 -> 228000
... A61: 46309 | B61: Banaras Looms | C61: Menswear | D61: 16 | E61: 3450 | F61: Yes | G61: =D61*E61 -> 55200

Sheet Messy Data
A1: Customer Name | B1: Phone | C1: City | D1: Amount
A2: Ravi Kumar | B2: 98480 12345 | C2: Hyderabad | D2: 12500
A3: Sneha Reddy | B3: 9848012346 | C3: Hyderabad | D3: 8200
A4: Anil Varma | B4: 9848012347 | C4: Vijayawada | D4: 15000
A5: Meena Iyer | B5: 9848012349 | C5: Bengaluru | D5: 4300
A6: Karthik Raj | B6: 9848012350 | C6: Chennai | D6: 9900
A7: Lakshmi Devi | B7: 9848012351 | C7: Warangal | D7: 7600
A8: Priya Sharma | B8: 9848012353 | C8: Hyderabad | D8: 21000
A9: Ramesh Babu | B9: 9848012354 | C9: Visakhapatnam | D9: 5400
